Metadata-Version: 2.1
Name: example_package_ha
Version: 0.0.1
Summary: A python implementation of FEAST -- a method for microbiome data deconvolution
Author-email: Ha Vu <havu73@ucla.edu>
Project-URL: Homepage, https://github.com/havu73/sampleproject
Project-URL: Bug Tracker, https://github.com/havu73/sampleproject/issues
Classifier: Programming Language :: Python :: 3
Classifier: License :: OSI Approved :: MIT License
Classifier: Operating System :: OS Independent
Requires-Python: >=3.7
License-File: LICENSE
